ckanext/__init__.py
ckanext/ap_cron/__init__.py
ckanext/ap_cron/cli.py
ckanext/ap_cron/col_renderers.py
ckanext/ap_cron/config.py
ckanext/ap_cron/const.py
ckanext/ap_cron/helpers.py
ckanext/ap_cron/interfaces.py
ckanext/ap_cron/model.py
ckanext/ap_cron/plugin.py
ckanext/ap_cron/types.py
ckanext/ap_cron/utils.py
ckanext/ap_cron/views.py
ckanext/ap_cron/collection/__init__.py
ckanext/ap_cron/collection/cron.py
ckanext/ap_cron/logic/__init__.py
ckanext/ap_cron/logic/action.py
ckanext/ap_cron/logic/auth.py
ckanext/ap_cron/logic/schema.py
ckanext/ap_cron/logic/validators.py
ckanext/ap_cron/migration/admin_panel_cron/env.py
ckanext/ap_cron/migration/admin_panel_cron/versions/2059dc28b9ad_add_ap_cron_job_table.py
ckanext/ap_cron/tests/conftest.py
ckanext/ap_cron/tests/factories.py
ckanext/ap_cron/tests/test_interface.py
ckanext/ap_cron/tests/logic/__init__.py
ckanext/ap_cron/tests/logic/test_action.py
ckanext/ap_cron/tests/logic/test_auth.py
ckanext/ap_cron/tests/logic/test_validators.py
ckanext/ap_doi/__init__.py
ckanext/ap_doi/collection.py
ckanext/ap_doi/config.py
ckanext/ap_doi/const.py
ckanext/ap_doi/plugin.py
ckanext/ap_doi/utils.py
ckanext/ap_doi/views.py
ckanext/ap_doi/logic/action.py
ckanext/ap_doi/logic/auth.py
ckanext/ap_doi/logic/schema.py
ckanext/ap_example/__init__.py
ckanext/ap_example/plugin.py
ckanext/ap_example/views.py
ckanext/ap_log/__init__.py
ckanext/ap_log/col_renderers.py
ckanext/ap_log/collection.py
ckanext/ap_log/log_handlers.py
ckanext/ap_log/model.py
ckanext/ap_log/plugin.py
ckanext/ap_log/views.py
ckanext/ap_log/logic/__init__.py
ckanext/ap_log/migration/admin_panel_log/env.py
ckanext/ap_log/migration/admin_panel_log/versions/fe11724f1867_init_table.py
ckanext/ap_main/__init__.py
ckanext/ap_main/col_renderers.py
ckanext/ap_main/config.py
ckanext/ap_main/helpers.py
ckanext/ap_main/interfaces.py
ckanext/ap_main/plugin.py
ckanext/ap_main/types.py
ckanext/ap_main/utils.py
ckanext/ap_main/collection/__init__.py
ckanext/ap_main/collection/base.py
ckanext_admin_panel-1.1.19.dist-info/LICENSE
ckanext_admin_panel-1.1.19.dist-info/METADATA
ckanext_admin_panel-1.1.19.dist-info/WHEEL
ckanext_admin_panel-1.1.19.dist-info/entry_points.txt
ckanext_admin_panel-1.1.19.dist-info/top_level.txt
ckanext_admin_panel-1.1.19.dist-info/RECORD
