Metadata-Version: 2.1
Name: ckanext-admin-panel
Version: 1.1.19
Summary: Custom admin panel for CKAN to expand default functionality
Author-email: DataShades <datashades@linkdigital.com.au>, Oleksandr Cherniavskyi <mutantsan@gmail.com>
Maintainer-email: DataShades <datashades@linkdigital.com.au>
License: AGPL
Project-URL: Homepage, https://github.com/DataShades/ckanext-admin-panel
Keywords: CKAN
Classifier: Development Status :: 4 - Beta
Classifier: License :: OSI Approved :: GNU Affero General Public License v3 or later (AGPLv3+)
Classifier: Programming Language :: Python :: 3.8
Classifier: Programming Language :: Python :: 3.9
Classifier: Programming Language :: Python :: 3.10
Requires-Python: >=3.8
License-File: LICENSE
Requires-Dist: typing-extensions
Requires-Dist: ckanext-toolbelt
Requires-Dist: ckanext-collection<1.0.0,>=0.1.21
Requires-Dist: croniter<3.0.0,>=2.0.1
Requires-Dist: cron-descriptor<2.0.0,>=1.4.0
Requires-Dist: ckanext-wysiwyg<1.0.0,>=0.1.0
Requires-Dist: ckanext-doi<4.0.0,>=3.1.12
Requires-Dist: ckanext-editable-config==0.0.6
Provides-Extra: test
Requires-Dist: pytest-ckan; extra == "test"
Requires-Dist: git-changelog; extra == "test"
